applib/__init__.py
applib/bin.py
setupapp-0.0.1.dist-info/DESCRIPTION.rst
setupapp-0.0.1.dist-info/METADATA
setupapp-0.0.1.dist-info/RECORD
setupapp-0.0.1.dist-info/WHEEL
setupapp-0.0.1.dist-info/entry_points.txt
setupapp-0.0.1.dist-info/metadata.json
setupapp-0.0.1.dist-info/top_level.txt
