Metadata-Version: 2.0
Name: setupapp
Version: 0.0.1
Summary: simple demo for python setup, author tom
Home-page: https://github.com/amlyj/setupapp
Author: tom.lee
Author-email: liyuanjunmail@qq.com
License: MIT
Platform: UNKNOWN
Requires-Dist: docopt
